{
  "ui": {
    "anchors": {
      "bottom": true,
      "left": true,
      "right": true,
      "top": true
    },
    "window": {
      "v_align": "fill",
      "h_align": "fill",
      "box": {
        "h_align": "center",
        "v_align": "start",
        "margins": {
          "bottom": 200,
          "top": 200
        },
        "orientation": "horizontal",
        "scroll": {
          "list": {
            "always_show": true,
            "item": {
              "activation_label": {
                "width": 20,
                "x_align": 1
              },
              "icon": {
                "theme": "Papirus"
              },
              "spacing": 5,
              "text": {
                "revert": true
              }
            },
            "max_height": 300,
            "max_width": 400,
            "min_width": 400,
            "width": 400
          },
          "overlay_scrolling": false
        },
        "search": {
          "spacing": 10,
          "v_align": "start",
          "width": 400
        },
        "spacing": 10
      }
    }
  }
}
